keras_unet_collection/__init__.py
keras_unet_collection/_backbone_zoo.py
keras_unet_collection/_model_att_unet_2d.py
keras_unet_collection/_model_r2_unet_2d.py
keras_unet_collection/_model_resunet_a_2d.py
keras_unet_collection/_model_swin_unet_2d.py
keras_unet_collection/_model_transunet_2d.py
keras_unet_collection/_model_u2net_2d.py
keras_unet_collection/_model_unet_2d.py
keras_unet_collection/_model_unet_3plus_2d.py
keras_unet_collection/_model_unet_plus_2d.py
keras_unet_collection/_model_vnet_2d.py
keras_unet_collection/activations.py
keras_unet_collection/backbones.py
keras_unet_collection/base.py
keras_unet_collection/layer_utils.py
keras_unet_collection/loss.py
keras_unet_collection/losses.py
keras_unet_collection/model_att_unet_2d.py
keras_unet_collection/model_r2_unet_2d.py
keras_unet_collection/model_resunet_a_2d.py
keras_unet_collection/model_u2net_2d.py
keras_unet_collection/model_unet_2d.py
keras_unet_collection/model_unet_3plus_2d.py
keras_unet_collection/model_unet_plus_2d.py
keras_unet_collection/models.py
keras_unet_collection/transformer_layers.py
keras_unet_collection/utils.py
keras_unet_collection-0.1.13.dist-info/LICENSE
keras_unet_collection-0.1.13.dist-info/METADATA
keras_unet_collection-0.1.13.dist-info/WHEEL
keras_unet_collection-0.1.13.dist-info/top_level.txt
keras_unet_collection-0.1.13.dist-info/RECORD
