Metadata-Version: 2.1
Name: keras-unet-collection
Version: 0.1.13
Summary: The Tensorflow, Keras implementation of U-net, V-net, U-net++, UNET 3+, Attention U-net, R2U-net, ResUnet-a, U^2-Net, TransUNET, and Swin-UNET with optional ImageNet-trained backbones.
Home-page: https://github.com/yingkaisha/keras-unet-collection
Author: Yingkai (Kyle) Sha
Author-email: yingkaisha@gmail.com
License: UNKNOWN
Platform: UNKNOWN
Classifier: Programming Language :: Python :: 3
Classifier: License :: OSI Approved :: MIT License
Classifier: Operating System :: OS Independent
Requires-Python: >=3.6
License-File: LICENSE
